fast_sugiyama-0.5.1.dist-info/METADATA
fast_sugiyama-0.5.1.dist-info/WHEEL
fast_sugiyama-0.5.1.dist-info/licenses/LICENSE
fast_sugiyama/__init__.py
fast_sugiyama/_fast_sugiyama.abi3.so
fast_sugiyama/_fast_sugiyama.pyi
fast_sugiyama/_types.py
fast_sugiyama/layout.py
fast_sugiyama/lib.py
fast_sugiyama/py.typed
fast_sugiyama-0.5.1.dist-info/RECORD
