Metadata-Version: 2.4
Name: fast-sugiyama
Version: 0.5.1
Classifier: Development Status :: 4 - Beta
Classifier: Environment :: Console
Classifier: Intended Audience :: Science/Research
Classifier: Intended Audience :: Developers
Classifier: License :: OSI Approved :: MIT License
Classifier: Operating System :: OS Independent
Classifier: Programming Language :: Python
Classifier: Programming Language :: Python :: 3
Classifier: Programming Language :: Python :: 3 :: Only
Classifier: Programming Language :: Python :: 3.11
Classifier: Programming Language :: Python :: 3.12
Classifier: Programming Language :: Python :: 3.13
Classifier: Programming Language :: Python :: 3.14
Classifier: Programming Language :: Python :: 3.15
Classifier: Programming Language :: Rust
Classifier: Topic :: Scientific/Engineering
Classifier: Topic :: Multimedia :: Graphics :: Presentation
Classifier: Topic :: Scientific/Engineering :: Visualization
Classifier: Typing :: Typed
Requires-Dist: rectangle-packer>=2 ; extra == 'all'
Requires-Dist: fast-sugiyama[all] ; extra == 'test'
Requires-Dist: pytest>=8 ; extra == 'test'
Requires-Dist: pytest-cov>=7 ; extra == 'test'
Requires-Dist: pytest-xdist>=3 ; extra == 'test'
Requires-Dist: networkx ; extra == 'test'
Requires-Dist: fast-sugiyama[test] ; extra == 'dev'
Requires-Dist: pre-commit>=3,<5 ; extra == 'dev'
Requires-Dist: ruff>=0.13 ; extra == 'dev'
Requires-Dist: matplotlib>=3.10 ; extra == 'dev'
Provides-Extra: all
Provides-Extra: test
Provides-Extra: dev
License-File: LICENSE
Summary: A fast and flexible hierarchical graph layout engine.
Keywords: graph-display,directed-graph,digraph,graph,pydot,layout,dot layout,graph layout,network,networkx,graphviz
Author-email: Austin Orr <austinmartinorr@gmail.com>
License-Expression: MIT
Requires-Python: >=3.11
